PostPyro-1.0.0.dist-info/METADATA
PostPyro-1.0.0.dist-info/WHEEL
PostPyro-1.0.0.dist-info/licenses/LICENSE
PostPyro/PostPyro.pyd
PostPyro/__init__.py
PostPyro/__init__.pyi
PostPyro-1.0.0.dist-info/RECORD
