Metadata-Version: 2.4
Name: PostPyro
Version: 1.0.0
Classifier: Development Status :: 5 - Production/Stable
Classifier: Intended Audience :: Developers
Classifier: License :: OSI Approved :: MIT License
Classifier: License :: OSI Approved :: Apache Software License
Classifier: Operating System :: OS Independent
Classifier: Programming Language :: Python :: 3
Classifier: Programming Language :: Python :: 3.8
Classifier: Programming Language :: Python :: 3.9
Classifier: Programming Language :: Python :: 3.10
Classifier: Programming Language :: Python :: 3.11
Classifier: Programming Language :: Python :: 3.12
Classifier: Programming Language :: Rust
Classifier: Topic :: Database
Classifier: Topic :: Software Development :: Libraries :: Python Modules
License-File: LICENSE
Summary: Ultra-fast PostgreSQL driver for Python built with Rust - Binary protocol, prepared statements, thread-safe
Keywords: postgresql,database,driver,rust,performance,binary-protocol,prepared-statements,thread-safe
Home-Page: https://github.com/magi8101/PostPyro
Author-email: Magi Sharma J <sharmamagi0@gmail.com>
Maintainer-email: Magi Sharma J <sharmamagi0@gmail.com>
License: MIT OR Apache-2.0
Requires-Python: >=3.8
Project-URL: Homepage, https://github.com/magi8101/PostPyro
Project-URL: Documentation, https://github.com/magi8101/PostPyro#readme
Project-URL: Repository, https://github.com/magi8101/PostPyro.git
Project-URL: Issues, https://github.com/magi8101/PostPyro/issues
Project-URL: Changelog, https://github.com/magi8101/PostPyro/blob/main/CHANGELOG.md
